parse_k8s_resources/__init__.py
parse_k8s_resources/main.py
parse_k8s_resources-0.0.3.dist-info/METADATA
parse_k8s_resources-0.0.3.dist-info/WHEEL
parse_k8s_resources-0.0.3.dist-info/entry_points.txt
parse_k8s_resources-0.0.3.dist-info/top_level.txt
parse_k8s_resources-0.0.3.dist-info/RECORD
